qsin/CD_dual_gap.py
qsin/ISLEPathCV.py
qsin/__init__.py
qsin/benchmarking.py
qsin/isle_path.py
qsin/path_subsampling.py
qsin/row_selection.py
qsin/sparse_solutions.py
qsin/sparse_solutions_hd.py
qsin/utils.py
qsin-0.11.16.data/scripts/infer_nets_batches.jl
qsin-0.11.16.data/scripts/infer_qlls.jl
qsin-0.11.16.data/scripts/sim_nets.R
qsin-0.11.16.dist-info/LICENSE
qsin-0.11.16.dist-info/METADATA
qsin-0.11.16.dist-info/WHEEL
qsin-0.11.16.dist-info/entry_points.txt
qsin-0.11.16.dist-info/top_level.txt
qsin-0.11.16.dist-info/RECORD
