Metadata-Version: 2.1
Name: qsin
Version: 0.11.16
Maintainer: Ulises Rosas
Classifier: Programming Language :: Python :: 3
License-File: LICENSE
Requires-Dist: numpy
Requires-Dist: numba
Requires-Dist: scikit-learn
